<?xml version="1.0" encoding="UTF-8" standalone="no"?><?Xpress productLine="ncc-clause" ?><clause id="_37cdf2aa-dad7-4d02-861b-9a71570e3224" outputclass="ncc-clause"><meta><facet building="Class 2"/><facet building="Class 3"/><facet building="Class 4"/><facet building="Class 5"/><facet building="Class 6"/><facet building="Class 7a"/><facet building="Class 7b"/><facet building="Class 8"/><facet building="Class 9a"/><facet building="Class 9b"/><facet building="Class 9c"/></meta><sptc>7.5.8</sptc><title id="_f6c2d88b-ef7b-464e-86b9-c17bd95146a3">Parapet cappings</title><archive-num>2019: 3.5.4.8</archive-num><subclause id="_a2cee7a1-b9be-4980-8134-af8d96a74299" outputclass="subclause"><title id="_8276b8ce-f745-4437-9739-ef2107c22df2">SubClause</title><num>1</num><p>Where a wall cladding is used to form a parapet wall, the cladding must be attached to a supporting frame and have a capping installed that complies with the following:</p><ol outputclass="alpha"><li id="_9801fba7-ef26-4676-9f52-0f356c994d31">Cappings must—<ol><li>be purpose made, machine-folded sheet metal or equivalent sections of a material compatible with all up and downstream metal roof covering materials in accordance with <xref xmlns:inv="urn:xpressauthor:xpressdocument" format="dita" href="/tmp/QppServer/Publishing/1c3f2f74-4ee1-4cdd-b1b4-53c91069d002/1557_1.5.0.xml#_1101b229-e577-4fab-a698-910dd580195d" id="_865d58e4-5d56-4ff1-a1db-afaaabdd4c05" inv:access="external" scope="local" type="subclause">7.2.2(2)</xref>; and</li><li>extend not less than 50 mm down the sides of the parapet; and</li><li>be separated from the supporting framing by a vapour permeable sarking installed in accordance with (f); and</li><li>be fixed with either self drilling screws or rivets with rubber washers at intervals of not more than 500 mm that do not penetrate the top of cappings, except at joints and corners.</li></ol></li><li id="_457d154b-5d4f-4dd7-9f7e-a3e345b87e5d">The top of the capping must slope a minimum of 5 degrees.</li><li id="_f5be322c-7cde-484d-917f-37c2938334aa">Joints in cappings must—<ol><li>overlap by not less than 50 mm in the direction of flow; and</li><li>be securely fastened at intervals of not more than 40 mm; and</li><li>have sealant installed between laps.</li></ol></li><li id="_edd5ff20-e076-4be3-b9d8-9e0586b1f40e">Fixing for cappings must be compatible with the capping material in accordance with <xref format="dita" href="/tmp/QppServer/Publishing/1c3f2f74-4ee1-4cdd-b1b4-53c91069d002/1557_1.5.0.xml#_638848f7-9f7b-4c77-974c-82efec494570" id="_2bb1c821-7b43-487d-ae2b-d6dcf0d16322" referencetype="Text" scope="local" synctargettext="false" type="ncc-clause">7.2.2</xref>.</li><li id="_ad475990-31cd-4bcf-a437-adc69a5de177">Lead cappings must not be used with prepainted steel or zinc/aluminium steel or on any roof if the roof is part of a <xref format="dita" href="/tmp/QppServer/Publishing/1c3f2f74-4ee1-4cdd-b1b4-53c91069d002/1250_0.7.0.xml#_762d6a54-e28c-400b-b9c5-5fceac019a05" id="_821b360e-4a15-4c97-aa39-1672cdd4afac" referencetype="Text" scope="local" synctargettext="false" type="abcb-glossentry">drinking water</xref> catchment area.</li><li id="_525d87a2-4d25-4fc5-9fb2-acbef10b7270">Sarking must comply with AS 4200.1 and be installed behind all wall cladding where parapets are installed, with—<ol><li>each adjoining sheet or roll being—<ol><li>overlapped not less than 150 mm; or</li><li>taped together; and</li></ol></li></ol><ol><li xmlns:inv="urn:xpressauthor:xpressdocument" inv:numbering="continue">sarking fixed to supporting members at not more than 300 mm centres.</li></ol></li></ol></subclause><callout id="_5ca7ab83-1eca-48a6-9bb8-5aed7cfa7c21"><callout-type ncc-info-type="info"/><p>For the purposes of 7.5.8(f), sarking is <xref xmlns:inv="urn:xpressauthor:xpressdocument" format="dita" href="/tmp/QppServer/Publishing/1c3f2f74-4ee1-4cdd-b1b4-53c91069d002/1432_4.0.0.xml#_af6fde9f-147d-4782-8b85-42044e80fd42" id="_de6d9e5f-88a9-481a-8045-9f4b8fb5234a" inv:access="external" scope="local" type="abcb-glossentry">required</xref> to be installed to the whole <xref xmlns:inv="urn:xpressauthor:xpressdocument" format="dita" href="/tmp/QppServer/Publishing/1c3f2f74-4ee1-4cdd-b1b4-53c91069d002/1267_2.3.0.xml#_d87c7cc0-d0b0-40ab-9a5b-d070ed6e115e" id="_33b2dee1-fc88-4c55-a3ae-0de1d5695ab2" inv:access="external" scope="local" type="abcb-glossentry">external wall</xref> which contains the parapet and extend to the top and back of the parapet. A gap should be provided between the sarking and the parapet capping to help control <xref xmlns:inv="urn:xpressauthor:xpressdocument" format="dita" href="/tmp/QppServer/Publishing/1c3f2f74-4ee1-4cdd-b1b4-53c91069d002/1224_0.8.0.xml#_7bd3fe3a-8528-4438-a6cb-6f4b43993774" id="_c4c92fe3-6bc5-473f-929b-af0d30e47659" inv:access="external" scope="local" type="abcb-glossentry">condensation</xref>.</p></callout></clause>