<?xml version="1.0" encoding="UTF-8" standalone="no"?><?Xpress productLine="ncc-clause" ?><clause id="_1d7b27aa-a5da-404f-8cc1-10c8601880d0" outputclass="ncc-clause"><meta><facet building="Class 2"/><facet building="Class 3"/><facet building="Class 4"/><facet building="Class 5"/><facet building="Class 6"/><facet building="Class 7a"/><facet building="Class 7b"/><facet building="Class 8"/><facet building="Class 9a"/><facet building="Class 9b"/><facet building="Class 9c"/><facet building="Class 10a"/><facet building="Class 10b"/><facet building="Class 10c"/></meta><sptc>H1D10</sptc><title id="_ead22741-5aea-48aa-a0f6-db094f9bc175">Flood hazard areas</title><archive-num>2019: 3.10.3</archive-num><clause-variation variation="SA" variation-type="DELETE">SA DELETE Clause</clause-variation><clause-variation deleted-text="Building work in designated flood hazard areas is regulated by the Building Act 1975 (QLD) and the Queensland Development Code MP 3.5 - Construction of buildings in flood hazard areas." variation="QLD" variation-type="DELETE">QLD DELETE Clause</clause-variation><clause-variation href="/tmp/QppServer/Publishing/1c3f2f74-4ee1-4cdd-b1b4-53c91069d002/2093_0.8.0.xml" variation="VIC" variation-type="REPLACE">VIC REPLACE Clause</clause-variation><subclause id="_f9f10b68-e79c-4168-a5ea-d2602621be3a" outputclass="subclause"><title id="_e5cf0821-bc8a-402a-8ef0-493be76228e7">SubClause</title><num>1</num><p><xref format="dita" href="/tmp/QppServer/Publishing/1c3f2f74-4ee1-4cdd-b1b4-53c91069d002/1395_4.0.0.xml#_f7304862-3529-49d7-9f62-352bcbcb6294" id="_293f3d6b-1d9a-4868-83d6-aa7503dc5b18" scope="local" type="abcb-glossentry">Performance Requirement</xref> <xref format="dita" href="/tmp/QppServer/Publishing/1c3f2f74-4ee1-4cdd-b1b4-53c91069d002/1781_2.4.0.xml#_de712d0a-85c7-4533-be8b-d5c1bbda428b" id="_ce22dc3f-6a27-418a-8a19-aeb8bbe1955c" scope="local" type="clause">H1P2</xref> for a Class 1 building constructed in a <xref format="dita" href="/tmp/QppServer/Publishing/1c3f2f74-4ee1-4cdd-b1b4-53c91069d002/1308_2.0.0.xml#_3220782b-f892-4b44-a260-95123b7a9ed0" id="_f5153211-af40-4c5f-9397-b445668a9ab3" scope="local" type="abcb-glossentry">flood hazard area</xref> is satisfied if the building is constructed in accordance with the ABCB Standard for Construction of Buildings in Flood Hazard Areas.</p></subclause></clause>