<?xml version="1.0" encoding="UTF-8" standalone="no"?><?Xpress productLine="ncc-clause" ?><clause xmlns:xt="urn:xpressauthor:trackchanges" id="_798b0efb-305e-47b4-9206-3e146fe28df6" outputclass="ncc-clause"><meta><facet building="Class 2"/><facet building="Class 3"/><facet building="Class 4"/><facet building="Class 5"/><facet building="Class 6"/><facet building="Class 7a"/><facet building="Class 7b"/><facet building="Class 8"/><facet building="Class 9a"/><facet building="Class 9b"/><facet building="Class 9c"/><facet building="Class 10a"/><facet building="Class 10b"/><facet building="Class 10c"/></meta><sptc>H8P1</sptc><title id="_44546800-1f5b-4f7b-acaf-b56a4986e122">Livable housing design</title><archive-num>New for 2022</archive-num><subclause id="_0b774c59-21f7-4496-9d29-092d46622d6e" outputclass="subclause"><title id="_0ed2f8bd-1ebc-4d14-90cf-92ebd6aa89f4">SubClause</title><num>1</num><p>A Class 1a building must be provided with—</p><ol outputclass="alpha"><li id="_22d65d88-87ff-41df-aa6a-ebf2ecd1cfcd">a continuous and step-free path to a dwelling entrance door from either—<ol><li id="_4eeb5773-26c7-4cf8-a6ef-4780fc27843e">the pedestrian entry at the allotment boundary; or</li><li>an appurtenant Class 10a garage or carport; or</li><li>a car parking space provided for the exclusive use of the occupants of the dwelling; and</li></ol></li><li id="_942bfde3-6d52-4721-b91a-b86d07dd98fe">at least one level and step-free entrance door into the dwelling from the access path <xref format="dita" href="/tmp/QppServer/Publishing/8bd50c59-637c-4a79-8565-09cd674ed7ed/1432_4.0.0.xml#_af6fde9f-147d-4782-8b85-42044e80fd42" id="_01341f73-7668-4192-90d1-63fffb0033e3" referencetype="Text" scope="local" synctargettext="false" type="abcb-glossentry">required</xref> by (a); and</li><li id="_b05b6d58-0c9b-4a14-add0-cbca84b15990">internal doors and corridors on the ground or entrance level which facilitate unimpeded movement between spaces; and</li><li id="_4e0dd61b-ce02-4b5d-a7b4-bfd0b455446d">a <xref format="dita" href="/tmp/QppServer/Publishing/8bd50c59-637c-4a79-8565-09cd674ed7ed/1445_0.13.0.xml#_b30a308f-eb9f-4549-a6c1-19d5f32a5272" id="_578a108c-8eda-4ff3-9c2b-d34b5c2d9524" referencetype="Text" scope="local" synctargettext="false" type="abcb-glossentry">sanitary compartment</xref> that—<ol><li id="_e4452642-3a8c-4b6f-a25f-f86bfa03a69a">facilitates independent access and use; and</li><li>is located on the ground or entry level; and</li></ol></li><li id="_62c9444b-ba8a-4d27-bf68-9ddc91299927">a shower that facilitates independent access and use; and</li><li id="_8b5e6aea-4ea0-46ba-8d7a-2e8d4575f50a">the walls of the <xref format="dita" href="/tmp/QppServer/Publishing/8bd50c59-637c-4a79-8565-09cd674ed7ed/1445_0.13.0.xml#_b30a308f-eb9f-4549-a6c1-19d5f32a5272" id="_fbfd2c2b-adee-4d34-9f81-0bbfe0e3bd67" referencetype="Text" scope="local" synctargettext="false" type="abcb-glossentry">sanitary compartment</xref> referred to in (d), the shower referred to in (e) and a bath (where installed, other than a freestanding bath) constructed so as to facilitate future installation of grabrails, or the like, in a way that minimises the removal of existing wall linings.</li></ol></subclause><callout id="_bcc17d46-7533-42ca-b33e-aa862c1123c8"><callout-type ncc-info-type="exemption"/><p>H8P1(a) need not be complied with if—</p><ol outputclass="alpha"><li id="_8f22d384-c86b-42d0-8725-292cf2b9eb94">step-free access cannot be provided from an appurtenant Class 10a garage or carport or a car parking space provided for the exclusive use of the occupants of the dwelling; and</li><li id="_5f6ad5ad-5ebe-4757-b803-ef68d05857e9">due to <xref format="dita" href="/tmp/QppServer/Publishing/8bd50c59-637c-4a79-8565-09cd674ed7ed/1463_0.4.0.xml#_fb3536f6-7ee5-4a29-a4da-402a8e1168dc" id="_703a4900-9b55-427f-a763-92ef9e49c188" referencetype="Text" scope="local" synctargettext="false" type="abcb-glossentry">site</xref> conditions, there is no other suitable location on which to construct the access path.</li></ol></callout></clause>