<?xml version="1.0" encoding="UTF-8" standalone="no"?><table-reference graph="None" id="_d1f91020-08d6-4854-89aa-bf4a54832f13"><num>H2V1b</num><title id="_7c1685d2-ebe1-4266-a916-f2d19d47a86f">Serviceability wind pressure</title><table id="_bff6985d-c694-4a31-9118-f7328d3b0979" keycol="1"><tgroup cols="2"><colspec colname="001" colnum="1" colwidth="216.00*"/><colspec colname="002" colnum="2" colwidth="216.00*"/><thead><row><entry>Stage number </entry><entry>Serviceability wind pressure</entry></row></thead><tbody><row><entry>1</entry><entry>15% to 30%</entry></row><row><entry>2</entry><entry>20% to 40%</entry></row><row><entry>3</entry><entry>30% to 60%</entry></row></tbody></tgroup></table></table-reference>