<?xml version="1.0" encoding="UTF-8" standalone="no"?><?Xpress productLine="ncc-clause" ?><clause id="_5c7207c3-1ca4-43a8-933e-d87516dc8742" outputclass="ncc-clause"><meta><facet building="Class 2"/><facet building="Class 3"/><facet building="Class 4"/><facet building="Class 5"/><facet building="Class 6"/><facet building="Class 7a"/><facet building="Class 7b"/><facet building="Class 7b"/><facet building="Class 9a"/><facet building="Class 9b"/><facet building="Class 9c"/><facet building="Class 10b"/></meta><sptc>8.4.4</sptc><title id="_d8117a75-993b-4186-9502-e49b3c013a3e">Full height framed glazed panels</title><archive-num>2019: 3.6.4.3</archive-num><subclause id="_3225fb44-c43d-4000-834f-19b3a4b61f8e" outputclass="subclause"><title id="_fac07f2d-6ad9-402c-8f64-4316aa7ac910">SubClause</title><num>1</num><p>A glazed panel located in a building so that it is capable of being mistaken for an <xref format="dita" href="/tmp/QppServer/Publishing/601d5817-38d4-46f4-a9ae-3e54027c73d5/1502_0.9.0.xml#_8681bc83-b7c7-44d1-a34e-27b92afea880" id="_00ec82b0-38ee-430a-997c-0c5eb90066fb" scope="local" type="abcb-glossentry">unobstructed opening</xref> must be glazed with Grade A safety glazing material in accordance with <xref format="dita" href="/tmp/QppServer/Publishing/601d5817-38d4-46f4-a9ae-3e54027c73d5/429_0.8.0.xml#_683329b1-c0f9-41f3-a7ec-31daa9e94819" id="_fb2b35b1-e311-4409-8253-7be62c8f58aa" referencetype="Text" scope="local" synctargettext="false" type="table-reference">Table 8.4.2</xref>.</p></subclause><subclause id="_3d559300-33cb-4a3f-aeea-ac77e954fb65" outputclass="subclause"><title id="_77761d19-6120-482f-baf3-fbfe996c4d31">SubClause</title><num>2</num><p>Glazed panels are not considered an <xref xmlns:inv="urn:xpressauthor:xpressdocument" format="dita" href="/tmp/QppServer/Publishing/601d5817-38d4-46f4-a9ae-3e54027c73d5/1502_0.9.0.xml#_8681bc83-b7c7-44d1-a34e-27b92afea880" id="_4fbf6cdf-a82b-42cf-8f4d-f18ebee22257" inv:access="external" scope="local" type="abcb-glossentry">unobstructed opening</xref> where any of the following apply:</p><ol outputclass="alpha"><li id="_ced9efa9-883a-4556-a0c0-a5488a4cee94">The clear opening width is not more than 500 mm.</li><li id="_43152adb-93c9-488a-8dcd-b6c41361ca99">The lowest sight line of the opening is not less than 500 mm above the highest abutting finished floor level.</li><li id="_44ac4f7d-d095-4da3-b259-0612bed8f35c">The glass is made apparent by means of transoms, colonial bars, other components of the glazing system, permanent motifs or other decorative treatment on or etched into the glass, of sufficient magnitude to be readily apparent, or the glass is opaquely coloured or patterned to indicate its presence.</li><li id="_b68f2290-711e-47b3-89b1-bd02b348281e">A chair rail or handrail not less than 40 mm thick, or the like, is provided at a height of not less than 700 mm above the adjoining ground level.</li><li id="_e2e0126c-1825-4fa0-9dc4-36225a48fc85">The difference in floor level on either side of the panel is greater than 1000 mm.</li></ol></subclause></clause>